Metadata-Version: 2.1
Name: myhttpcatlab
Version: 0.0.3
Summary: Httpcat Resource Storage SDK
Home-page: https://github.com/lazy-wangxl/myhttpcatlab
Author: Httpcat Information Technologies Co., Ltd.
Author-email: xiaolongwang501@gmail.com
Maintainer-email: xiaolongwang501@gmail.com
License: MIT
Download-URL: https://github.com/lazy-wangxl/myhttpcatlab
Project-URL: Source, https://github.com/lazy-wangxl/myhttpcatlab.git
Platform: any
Classifier: Intended Audience :: Developers
Classifier: License :: OSI Approved :: MIT License
Classifier: Operating System :: OS Independent
Classifier: Programming Language :: Python
Classifier: Programming Language :: Python :: 2
Classifier: Programming Language :: Python :: 2.6
Classifier: Programming Language :: Python :: 2.7
Classifier: Programming Language :: Python :: 3
Classifier: Programming Language :: Python :: 3.3
Classifier: Programming Language :: Python :: 3.4
Classifier: Programming Language :: Python :: 3.5
Classifier: Programming Language :: Python :: 3.6
Classifier: Programming Language :: Python :: 3.7
Classifier: Topic :: Internet :: WWW/HTTP :: Dynamic Content
Classifier: Topic :: Software Development :: Libraries :: Python Modules
Provides-Extra: dev
